cumin/__init__.py
cumin/cli.py
cumin/color.py
cumin/grammar.py
cumin/query.py
cumin/transport.py
cumin/backends/__init__.py
cumin/backends/direct.py
cumin/backends/knownhosts.py
cumin/backends/openstack.py
cumin/backends/puppetdb.py
cumin/transports/__init__.py
cumin/transports/clustershell.py
cumin-5.1.1.data/data/share/doc/cumin/examples/aliases.yaml
cumin-5.1.1.data/data/share/doc/cumin/examples/config.yaml
cumin-5.1.1.dist-info/LICENSE
cumin-5.1.1.dist-info/METADATA
cumin-5.1.1.dist-info/WHEEL
cumin-5.1.1.dist-info/entry_points.txt
cumin-5.1.1.dist-info/top_level.txt
cumin-5.1.1.dist-info/RECORD
